flusstools/__init__.py
flusstools/helpers.py
flusstools/import_mgmt.py
flusstools/var_config.py
flusstools/bedanalyst/__init__.py
flusstools/bedanalyst/config.py
flusstools/bedanalyst/degree_clogging.py
flusstools/bedanalyst/interp_z2shp.py
flusstools/bedanalyst/utils.py
flusstools/fuzzycorr/__init__.py
flusstools/fuzzycorr/convertor.py
flusstools/fuzzycorr/fuzzycomp.py
flusstools/fuzzycorr/fuzzycorr.py
flusstools/fuzzycorr/plotter.py
flusstools/fuzzycorr/prepro.py
flusstools/geotools/__init__.py
flusstools/geotools/dataset_mgmt.py
flusstools/geotools/geotools.py
flusstools/geotools/kml.py
flusstools/geotools/kmx_parser.py
flusstools/geotools/raster_mgmt.py
flusstools/geotools/shortest_path.py
flusstools/geotools/shp_mgmt.py
flusstools/geotools/srs_mgmt.py
flusstools/lidartools/__init__.py
flusstools/lidartools/hdf_analyst.py
flusstools/lidartools/laspy_config.py
flusstools/lidartools/laspy_main.py
flusstools/lidartools/laspy_processor.py
flusstools/lidartools/lastools_GUI.py
flusstools/lidartools/lastools_core.py
flusstools/lidartools/lastools_fun.py
flusstools-1.1.14.dist-info/METADATA
flusstools-1.1.14.dist-info/WHEEL
flusstools-1.1.14.dist-info/licenses/LICENSE
flusstools-1.1.14.dist-info/RECORD
