Metadata-Version: 2.4
Name: flusstools
Version: 1.1.14
Summary: A Python toolbox for river and floodplain analysis.
Project-URL: Homepage, https://github.com/ecohydraulics/flusstools-docs
Project-URL: Bug Tracker, https://github.com/ecohydraulics/flusstools-pckg/issues
Author-email: FlussTeam / Hydro‑Informatics <schwindt.water@gmail.com>
License: BSD 3-Clause License
License-File: LICENSE
Keywords: Python,QGIS,geospatial,gis,hydraulic‑engineering,hydroinformatics,hydro‑morphology,numerical,rivers,schwindt,simulations
Classifier: Development Status :: 4 - Beta
Classifier: Intended Audience :: Science/Research
Classifier: License :: OSI Approved :: BSD License
Classifier: Programming Language :: Python :: 3
Classifier: Programming Language :: Python :: 3 :: Only
Classifier: Programming Language :: Python :: 3.13
Classifier: Topic :: Scientific/Engineering :: GIS
Requires-Python: >=3.10
Requires-Dist: alphashape>=1.3.1
Requires-Dist: earthpy>=0.9.4
Requires-Dist: geojson>=3.2
Requires-Dist: geopandas>=1.1
Requires-Dist: h5py>=3.14
Requires-Dist: laspy>=2.6
Requires-Dist: mapclassify>=2.9
Requires-Dist: matplotlib>=3.10
Requires-Dist: networkx>=3.5
Requires-Dist: numpy>=2.3
Requires-Dist: openpyxl>=3.1
Requires-Dist: pandas>=2.3
Requires-Dist: pyshp>=2.3.1
Requires-Dist: rasterio>=1.4
Requires-Dist: rasterstats>=0.20
Requires-Dist: scipy>=1.16
Requires-Dist: shapely>=2.1
Requires-Dist: tabulate>=0.9
Provides-Extra: docs
Requires-Dist: myst-parser>=2.0; extra == 'docs'
Requires-Dist: sphinx-book-theme>=1.1; extra == 'docs'
Requires-Dist: sphinx>=7.3; extra == 'docs'
Requires-Dist: sphinxcontrib-bibtex>=2.6; extra == 'docs'
Provides-Extra: style
Requires-Dist: pre-commit>=3.7; extra == 'style'
Requires-Dist: ruff>=0.4; extra == 'style'
Provides-Extra: test
Requires-Dist: pytest-cov>=5.0; extra == 'test'
Requires-Dist: pytest-xdist>=3.5; extra == 'test'
Requires-Dist: pytest>=8.0; extra == 'test'
